query_to_df.py
query_to_df-0.1.dist-info/METADATA
query_to_df-0.1.dist-info/WHEEL
query_to_df-0.1.dist-info/top_level.txt
query_to_df-0.1.dist-info/RECORD
